Workbook

Sheet Read_Me
A1: All Data has been taken from the Federal Reserve Economic Data, Federal Reserve Bank of St. Louis. | C1: POP
A3: Tickers:
A5: GDP | B5: Gross Domestic Product, Billions of Dollars, Quarterly, Seasonally Adjusted Annual Rate
A6: GDPDEF | B6: Gross Domestic Product: Implicit Price Deflator, Index 2017=100, Quarterly, Seasonally Adjusted
A7: PCECC96 | B7: Personal Consumption Expenditures, Billions of Dollars, Quarterly, Seasonally Adjusted Annual Rate
A8: CPIAUCSL | B8: Consumer Price Index for All Urban Consumers: All Items in U.S. City Average, Percent Change from Year Ago, Quarterly, Seasonally Adjusted
A9: GFDEBTN | B9: Federal Debt: Total Public Debt, Millions of Dollars, Quarterly, Not Seasonally Adjusted
A10: FEDFUNDS | B10: Federal Funds Effective Rate, Percent, Quarterly, Not Seasonally Adjusted
A11: LFWA64TTUSM647S | B11: Infra-Annual Labor Statistics: Working-Age Population Total: From 15 to 64 Years for United States

Sheet Table
A1: Variables | B1: Standard deviation (%) | F1: Correlation with output
B2: Data | C2: Reg M | D2: Reg F | E2: Coexist Reg | F2: Data | G2: Reg M | H2: Reg F | I2: Coexist Reg
A3: Output | B3: 1.244 | F3: 1
A4: Household consumption | B4: 1.236 | F4: 0.884
A5: Inflation (CPI) | B5: 0.536 | F5: 0.344
A6: Public debt | B6: 2.552 | F6: -0.356
A7: Federal funds rate | B7: 0.568 | F7: 0.282
A10: *Final Values calculated using r

Sheet Logged Data
A1: Date | B1: Log_GDP | C1: Log_Cons | D1: Log_Debt | E1: Inflation | F1: FFR
A2: 29952 | B2: =GDP!F2 -> 3.9106396 | C2: =Consumption!D2 -> 3.4450974 | D2: =Total_Public_Debt!G2 -> 2.7840285 | E2: =Inflation!C6 -> 0.0088837224 | F2: =Federal_Funds_Effective_Rate!C2 -> 0.1423
A3: 30042 | B3: =GDP!F3 -> 3.9110073 | C3: =Consumption!D3 -> 3.4439536 | D3: =Total_Public_Debt!G3 -> 2.7840613 | E3: =Inflation!C7 -> 0.014450317 | F3: =Federal_Funds_Effective_Rate!C3 -> 0.1451
A4: 30133 | B4: =GDP!F4 -> 3.9041399 | C4: =Consumption!D4 -> 3.4475986 | D4: =Total_Public_Debt!G4 -> 2.8231309 | E4: =Inflation!C8 -> 0.017360134 | F4: =Federal_Funds_Effective_Rate!C4 -> 0.1101
A5: 30225 | B5: =GDP!F5 -> 3.9010864 | C5: =Consumption!D5 -> 3.4615162 | D5: =Total_Public_Debt!G5 -> 2.8564382 | E5: =Inflation!C9 -> 0.0030727316 | F5: =Federal_Funds_Effective_Rate!C5 -> 0.0929
A6: 30317 | B6: =GDP!F6 -> 3.9152526 | C6: =Consumption!D6 -> 3.4724391 | D6: =Total_Public_Debt!G6 -> 2.8888431 | E6: =Inflation!C10 -> 0.0006841412 | F6: =Federal_Funds_Effective_Rate!C6 -> 0.0865
A7: 30407 | B7: =GDP!F7 -> 3.9331134 | C7: =Consumption!D7 -> 3.4879414 | D7: =Total_Public_Debt!G7 -> 2.9353867 | E7: =Inflation!C11 -> 0.011561224 | F7: =Federal_Funds_Effective_Rate!C7 -> 0.088
A8: 30498 | B8: =GDP!F8 -> 3.9507027 | C8: =Consumption!D8 -> 3.5035221 | D8: =Total_Public_Debt!G8 -> 2.9653592 | E8: =Inflation!C12 -> 0.0097545721 | F8: =Federal_Funds_Effective_Rate!C8 -> 0.0946
A9: 30590 | B9: =GDP!F9 -> 3.9686848 | C9: =Consumption!D9 -> 3.5166579 | D9: =Total_Public_Debt!G9 -> 2.9791653 | E9: =Inflation!C13 -> 0.00999001 | F9: =Federal_Funds_Effective_Rate!C9 -> 0.0943
A10: 30682 | B10: =GDP!F10 -> 3.9857078 | C10: =Consumption!D10 -> 3.5225967 | D10: =Total_Public_Debt!G10 -> 3.0036637 | E10: =Inflation!C14 -> 0.014174085 | F10: =Federal_Funds_Effective_Rate!C10 -> 0.0969
A11: 30773 | B11: =GDP!F11 -> 3.9998808 | C11: =Consumption!D11 -> 3.5335465 | D11: =Total_Public_Debt!G11 -> 3.0250832 | E11: =Inflation!C15 -> 0.00943111 | F11: =Federal_Funds_Effective_Rate!C11 -> 0.1056
A12: 30864 | B12: =GDP!F12 -> 4.0069086 | C12: =Consumption!D12 -> 3.5383654 | D12: =Total_Public_Debt!G12 -> 3.052289 | E12: =Inflation!C16 -> 0.0086956522 | F12: =Federal_Funds_Effective_Rate!C12 -> 0.1139
A13: 30956 | B13: =GDP!F13 -> 4.0124529 | C13: =Consumption!D13 -> 3.5486072 | D13: =Total_Public_Debt!G13 -> 3.0982965 | E13: =Inflation!C17 -> 0.0086206897 | F13: =Federal_Funds_Effective_Rate!C13 -> 0.0927
... A176: 45839 | B176: =GDP!F176 -> 4.7293927 | C176: =Consumption!D176 -> 4.35877 | D176: =Total_Public_Debt!G176 -> 4.9202506 | E176: =Inflation!C180 -> 0.0076343731 | F176: =Federal_Funds_Effective_Rate!C176 -> 0.0429

Sheet GDP
A1: Date | B1: GDP | C1: GDPDEF | D1: Real GDP | E1: Real GDP Per Capita | F1: Log_GDP
A2: 29952 | B2: 3274.302 | C2: 44.88 | D2: =B2/(C2)*100 -> 7295.6818 | E2: =D2/(Working_Age_Population!B2/1000000) -> 49.930878 | F2: =LN(E2) -> 3.9106396
A3: 30042 | B3: 3331.972 | C3: 45.463 | D3: =B3/(C3)*100 -> 7328.9752 | E3: =D3/(Working_Age_Population!B3/1000000) -> 49.949239 | F3: =LN(E3) -> 3.9110073
A4: 30133 | B4: 3366.322 | C4: 46.108 | D4: =B4/(C4)*100 -> 7300.9499 | E4: =D4/(Working_Age_Population!B4/1000000) -> 49.607394 | F4: =LN(E4) -> 3.9041399
A5: 30225 | B5: 3402.561 | C5: 46.586 | D5: =B5/(C5)*100 -> 7303.8273 | E5: =D5/(Working_Age_Population!B5/1000000) -> 49.456148 | F5: =LN(E5) -> 3.9010864
A6: 30317 | B6: 3473.413 | C6: 46.938 | D6: =B6/(C6)*100 -> 7400.0021 | E6: =D6/(Working_Age_Population!B6/1000000) -> 50.161741 | F6: =LN(E6) -> 3.9152526
A7: 30407 | B7: 3578.848 | C7: 47.286 | D7: =B7/(C7)*100 -> 7568.515 | E7: =D7/(Working_Age_Population!B7/1000000) -> 51.06572 | F7: =LN(E7) -> 3.9331134
A8: 30498 | B8: 3689.179 | C8: 47.789 | D8: =B8/(C8)*100 -> 7719.7242 | E8: =D8/(Working_Age_Population!B8/1000000) -> 51.971877 | F8: =LN(E8) -> 3.9507027
A9: 30590 | B9: 3794.706 | C9: 48.151 | D9: =B9/(C9)*100 -> 7880.8457 | E9: =D9/(Working_Age_Population!B9/1000000) -> 52.91489 | F9: =LN(E9) -> 3.9686848
A10: 30682 | B10: 3908.054 | C10: 48.639 | D10: =B10/(C10)*100 -> 8034.8157 | E10: =D10/(Working_Age_Population!B10/1000000) -> 53.823371 | F10: =LN(E10) -> 3.9857078
A11: 30773 | B11: 4009.601 | C11: 49.055 | D11: =B11/(C11)*100 -> 8173.6846 | E11: =D11/(Working_Age_Population!B11/1000000) -> 54.591643 | F11: =LN(E11) -> 3.9998808
A12: 30864 | B12: 4084.25 | C12: 49.491 | D12: =B12/(C12)*100 -> 8252.5106 | E12: =D12/(Working_Age_Population!B12/1000000) -> 54.976653 | F12: =LN(E12) -> 4.0069086
A13: 30956 | B13: 4148.551 | C13: 49.861 | D13: =B13/(C13)*100 -> 8320.2322 | E13: =D13/(Working_Age_Population!B13/1000000) -> 55.282307 | F13: =LN(E13) -> 4.0124529
... A176: 45839 | B176: 31098.027 | C176: 129.43 | D176: =B176/(C176)*100 -> 24026.908 | E176: =D176/(Working_Age_Population!B176/1000000) -> 113.22678 | F176: =LN(E176) -> 4.7293927

Sheet Consumption
A1: Date | B1: PCECC96 | C1: Real Consumption Per Capita | D1: Log_Cons
A2: 29952 | B2: 4580.19 | C2: =B2/(Working_Age_Population!B2/1000000) -> 31.346338 | D2: =LN(C2) -> 3.4450974
A3: 30042 | B3: 4594.142 | C3: =B3/(Working_Age_Population!B3/1000000) -> 31.310502 | D3: =LN(C3) -> 3.4439536
A4: 30133 | B4: 4624.939 | C4: =B4/(Working_Age_Population!B4/1000000) -> 31.424838 | D4: =LN(C4) -> 3.4475986
A5: 30225 | B5: 4705.953 | C5: =B5/(Working_Age_Population!B5/1000000) -> 31.865253 | D5: =LN(C5) -> 3.4615162
A6: 30317 | B6: 4752.481 | C6: =B6/(Working_Age_Population!B6/1000000) -> 32.215223 | D6: =LN(C6) -> 3.4724391
A7: 30407 | B7: 4849.254 | C7: =B7/(Working_Age_Population!B7/1000000) -> 32.718525 | D7: =LN(C7) -> 3.4879414
A8: 30498 | B8: 4936.211 | C8: =B8/(Working_Age_Population!B8/1000000) -> 33.232295 | D8: =LN(C8) -> 3.5035221
A9: 30590 | B9: 5014.874 | C9: =B9/(Working_Age_Population!B9/1000000) -> 33.671705 | D9: =LN(C9) -> 3.5166579
A10: 30682 | B10: 5056.492 | C10: =B10/(Working_Age_Population!B10/1000000) -> 33.87227 | D10: =LN(C10) -> 3.5225967
A11: 30773 | B11: 5127.332 | C11: =B11/(Working_Age_Population!B11/1000000) -> 34.245202 | D11: =LN(C11) -> 3.5335465
A12: 30864 | B12: 5165.357 | C12: =B12/(Working_Age_Population!B12/1000000) -> 34.410624 | D12: =LN(C12) -> 3.5383654
A13: 30956 | B13: 5232.266 | C13: =B13/(Working_Age_Population!B13/1000000) -> 34.764863 | D13: =LN(C13) -> 3.5486072
... A176: 45839 | B176: 16585.878 | C176: =B176/(Working_Age_Population!B176/1000000) -> 78.160935 | D176: =LN(C176) -> 4.35877

Sheet Inflation
A1: Date | B1: CPIAUCSL | C1: Inflation
A2: 29587 | B2: 87.933
A3: 29677 | B3: 89.767
A4: 29768 | B4: 92.267
A5: 29860 | B5: 93.767
A6: 29952 | B6: 94.6 | C6: =(B6-B5)/B5 -> 0.0088837224
A7: 30042 | B7: 95.967 | C7: =(B7-B6)/B6 -> 0.014450317
A8: 30133 | B8: 97.633 | C8: =(B8-B7)/B7 -> 0.017360134
A9: 30225 | B9: 97.933 | C9: =(B9-B8)/B8 -> 0.0030727316
A10: 30317 | B10: 98 | C10: =(B10-B9)/B9 -> 0.0006841412
A11: 30407 | B11: 99.133 | C11: =(B11-B10)/B10 -> 0.011561224
A12: 30498 | B12: 100.1 | C12: =(B12-B11)/B11 -> 0.0097545721
A13: 30590 | B13: 101.1 | C13: =(B13-B12)/B12 -> 0.00999001
A14: 30682 | B14: 102.533 | C14: =(B14-B13)/B13 -> 0.014174085
A15: 30773 | B15: 103.5 | C15: =(B15-B14)/B14 -> 0.00943111
A16: 30864 | B16: 104.4 | C16: =(B16-B15)/B15 -> 0.0086956522
A17: 30956 | B17: 105.3 | C17: =(B17-B16)/B16 -> 0.0086206897
... A180: 45839 | B180: 323.235 | C180: =(B180-B179)/B179 -> 0.0076343731

Sheet Government_Expenditure
A1: Date | B1: W019RCQ027SBEA | C1: GovExpend to GDP
A2: 29952 | B2: 776.728 | C2: =B2/GDP!B2 -> 0.23721941 | E2: Average over Sample Period | F2: =AVERAGE(C3:C177) -> 0.22969125
A3: 30042 | B3: 796.653 | C3: =B3/GDP!B3 -> 0.23909355
A4: 30133 | B4: 822.7 | C4: =B4/GDP!B4 -> 0.24439136
A5: 30225 | B5: 850.183 | C5: =B5/GDP!B5 -> 0.24986562
A6: 30317 | B6: 866.856 | C6: =B6/GDP!B6 -> 0.24956894
A7: 30407 | B7: 871.501 | C7: =B7/GDP!B7 -> 0.24351439
A8: 30498 | B8: 896.644 | C8: =B8/GDP!B8 -> 0.24304703
A9: 30590 | B9: 900.154 | C9: =B9/GDP!B9 -> 0.23721311
A10: 30682 | B10: 913.474 | C10: =B10/GDP!B10 -> 0.2337414
A11: 30773 | B11: 934.407 | C11: =B11/GDP!B11 -> 0.23304239
A12: 30864 | B12: 950.602 | C12: =B12/GDP!B12 -> 0.23274824
A13: 30956 | B13: 987.607 | C13: =B13/GDP!B13 -> 0.23806071
A14: 31048 | B14: 1000.093 | C14: =B14/GDP!B14 -> 0.23641922
... A176: 45839 | B176: 7766.78 | C176: =B176/GDP!B176 -> 0.24975154

Sheet Total_Public_Debt
A1: Date | B1: GFDEBTN | C1: In Billions | D1: GDPDEF | E1: Real Public Debt | F1: Real Public Debt Per Capita | G1: Log_Debt
A2: 29952 | B2: 1061299 | C2: =B2/1000 -> 1061.299 | D2: 44.88 | E2: =C2/(D2/100) -> 2364.7482 | F2: =E2/(Working_Age_Population!B2/1000000) -> 16.184088 | G2: =LN(F2) -> 2.7840285
A3: 30042 | B3: 1079630 | C3: =B3/1000 -> 1079.63 | D3: 45.463 | E3: =C3/(D3/100) -> 2374.7443 | F3: =E3/(Working_Age_Population!B3/1000000) -> 16.184619 | G3: =LN(F3) -> 2.7840613
A4: 30133 | B4: 1142035 | C4: =B4/1000 -> 1142.035 | D4: 46.108 | E4: =C4/(D4/100) -> 2476.8695 | F4: =E4/(Working_Age_Population!B4/1000000) -> 16.829459 | G4: =LN(F4) -> 2.8231309
A5: 30225 | B5: 1197074 | C5: =B5/1000 -> 1197.074 | D5: 46.586 | E5: =C5/(D5/100) -> 2569.6003 | F5: =E5/(Working_Age_Population!B5/1000000) -> 17.399444 | G5: =LN(F5) -> 2.8564382
A6: 30317 | B6: 1244493 | C6: =B6/1000 -> 1244.493 | D6: 46.938 | E6: =C6/(D6/100) -> 2651.355 | F6: =E6/(Working_Age_Population!B6/1000000) -> 17.972506 | G6: =LN(F6) -> 2.8888431
A7: 30407 | B7: 1319581 | C7: =B7/1000 -> 1319.581 | D7: 47.286 | E7: =C7/(D7/100) -> 2790.6378 | F7: =E7/(Working_Age_Population!B7/1000000) -> 18.828783 | G7: =LN(F7) -> 2.9353867
A8: 30498 | B8: 1377211 | C8: =B8/1000 -> 1377.211 | D8: 47.789 | E8: =C8/(D8/100) -> 2881.8577 | F8: =E8/(Working_Age_Population!B8/1000000) -> 19.401672 | G8: =LN(F8) -> 2.9653592
A9: 30590 | B9: 1410702 | C9: =B9/1000 -> 1410.702 | D9: 48.151 | E9: =C9/(D9/100) -> 2929.746 | F9: =E9/(Working_Age_Population!B9/1000000) -> 19.67139 | G9: =LN(F9) -> 2.9791653
A10: 30682 | B10: 1463741 | C10: =B10/1000 -> 1463.741 | D10: 48.639 | E10: =C10/(D10/100) -> 3009.3978 | F10: =E10/(Working_Age_Population!B10/1000000) -> 20.15926 | G10: =LN(F10) -> 3.0036637
A11: 30773 | B11: 1512697 | C11: =B11/1000 -> 1512.697 | D11: 49.055 | E11: =C11/(D11/100) -> 3083.6755 | F11: =E11/(Working_Age_Population!B11/1000000) -> 20.595719 | G11: =LN(F11) -> 3.0250832
A12: 30864 | B12: 1572267 | C12: =B12/1000 -> 1572.267 | D12: 49.491 | E12: =C12/(D12/100) -> 3176.8746 | F12: =E12/(Working_Age_Population!B12/1000000) -> 21.163733 | G12: =LN(F12) -> 3.052289
A13: 30956 | B13: 1662966 | C13: =B13/1000 -> 1662.966 | D13: 49.861 | E13: =C13/(D13/100) -> 3335.2039 | F13: =E13/(Working_Age_Population!B13/1000000) -> 22.16017 | G13: =LN(F13) -> 3.0982965
... A176: 45839 | B176: 37637553 | C176: =B176/1000 -> 37637.553 | D176: 129.43 | E176: =C176/(D176/100) -> 29079.466 | F176: =E176/(Working_Age_Population!B176/1000000) -> 137.03696 | G176: =LN(F176) -> 4.9202506

Sheet Federal_Funds_Effective_Rate
A1: Date | B1: FEDFUNDS
A2: 29952 | B2: 14.23 | C2: =B2/100 -> 0.1423
A3: 30042 | B3: 14.51 | C3: =B3/100 -> 0.1451
A4: 30133 | B4: 11.01 | C4: =B4/100 -> 0.1101
A5: 30225 | B5: 9.29 | C5: =B5/100 -> 0.0929
A6: 30317 | B6: 8.65 | C6: =B6/100 -> 0.0865
A7: 30407 | B7: 8.8 | C7: =B7/100 -> 0.088
A8: 30498 | B8: 9.46 | C8: =B8/100 -> 0.0946
A9: 30590 | B9: 9.43 | C9: =B9/100 -> 0.0943
A10: 30682 | B10: 9.69 | C10: =B10/100 -> 0.0969
A11: 30773 | B11: 10.56 | C11: =B11/100 -> 0.1056
A12: 30864 | B12: 11.39 | C12: =B12/100 -> 0.1139
A13: 30956 | B13: 9.27 | C13: =B13/100 -> 0.0927
... A177: 45931 | B177: 3.9 | C177: =B177/100 -> 0.039

Sheet Working_Age_Population
A1: Date | B1: LFWA64TTUSM647S
A2: 29952 | B2: 146115633
A3: 30042 | B3: 146728467
A4: 30133 | B4: 147174633
A5: 30225 | B5: 147682900
A6: 30317 | B6: 147522833
A7: 30407 | B7: 148211267
A8: 30498 | B8: 148536567
A9: 30590 | B9: 148934367
A10: 30682 | B10: 149281167
A11: 30773 | B11: 149724100
A12: 30864 | B12: 150109367
A13: 30956 | B13: 150504433
... A176: 45839 | B176: 212201633
